{
  "vlrEducacaoRealizado": 28.44,
  "vlrEducacaoBaseCalcDec": 96634903.69,
  "vlrEducacaoBaseCalc": "96.6 Milhões",
  "vlrEducacaoTotalGastoDec": 27486102.83,
  "vlrEducacaoTotalGasto": "27.4 Milhões",
  "vlrSaudeRealizado": 27.03,
  "vlrSaudeBaseCalcDec": 96634903.69,
  "vlrSaudeBaseCalc": "96.6 Milhões",
  "vlrSaudeTotalGastoDec": 26120802.05,
  "vlrSaudeTotalGasto": "26.1 Milhões",
  "vlrPessoalRealizado": 54.25,
  "vlrPessoalBaseCalcDec": 128167122.8,
  "vlrPessoalBaseCalc": "128.1 Milhões",
  "vlrPessoalTotalGastoDec": 69527599.10,
  "vlrPessoalTotalGasto": "69.5 Milhões",
  "vlrPrevRec": 150.9,
  "dscEscalaPrevRec": "Milhões",
  "vlrTotalRec": 129.0,
  "dscEscalaTotalRec": "Milhões",
  "vlrPrevDesp": 150.9,
  "dscEscalaPrevDesp": "Milhões",
  "vlrTotalDesp": 133.5,
  "dscEscalaTotalDesp": "Milhões",
  "vlrTotalDespF": 133507366.09,
  "vlrTotalRecF": 129397995.41,
  "vlrPrevRecF": 150920360.0,
  "vlrPrevDespF": 150920360.0
}