{
  "vlrEducacaoRealizado": 26.08,
  "vlrEducacaoBaseCalcDec": 106467850.28,
  "vlrEducacaoBaseCalc": "106.4 Milhões",
  "vlrEducacaoTotalGastoDec": 27766866.79,
  "vlrEducacaoTotalGasto": "27.7 Milhões",
  "vlrSaudeRealizado": 33.4,
  "vlrSaudeBaseCalcDec": 103433354.44,
  "vlrSaudeBaseCalc": "103.4 Milhões",
  "vlrSaudeTotalGastoDec": 34551463.27,
  "vlrSaudeTotalGasto": "34.5 Milhões",
  "vlrPessoalRealizado": 47.47,
  "vlrPessoalBaseCalcDec": 170864584.17,
  "vlrPessoalBaseCalc": "170.8 Milhões",
  "vlrPessoalTotalGastoDec": 81113520.58,
  "vlrPessoalTotalGasto": "81.1 Milhões",
  "vlrPrevRec": 199.7,
  "dscEscalaPrevRec": "Milhões",
  "vlrTotalRec": 173.5,
  "dscEscalaTotalRec": "Milhões",
  "vlrPrevDesp": 199.7,
  "dscEscalaPrevDesp": "Milhões",
  "vlrTotalDesp": 164.0,
  "dscEscalaTotalDesp": "Milhões",
  "vlrTotalDespF": 164201504.11,
  "vlrTotalRecF": 173559673.17,
  "vlrPrevRecF": 199708000.0,
  "vlrPrevDespF": 199708000.0
}